etc/init.d/smart_daemon
smartsched/daemon/__init__.py
smartsched/daemon/base_daemon.py
smartsched/daemon/base_strategy.py
smartsched/daemon/smart_daemon.py
smartsched.daemon-0.0.17.dist-info/METADATA
smartsched.daemon-0.0.17.dist-info/RECORD
smartsched.daemon-0.0.17.dist-info/WHEEL
smartsched.daemon-0.0.17.dist-info/top_level.txt
usr/bin/SmartDaemon
